{"adult": false, "backdrop_path": "https://image.tmdb.org/t/p/original/jRi6AKMPLnMtsFtWY0FUXZOlnVb.jpg", "belongs_to_collection": {"id": 473971, "name": "Daddy's Home Collection", "poster_path": "/sKjm3JtHz3Z5ggyNZC4IEz4z4Dl.jpg", "backdrop_path": "/16w6DLmX0OqGT5qBdMpfpWh4VkU.jpg"}, "budget": 69000000, "genres": [{"id": 35, "name": "Phim Hài"}], "homepage": "http://www.daddyshomemovie.com/", "id": 419680, "imdb_id": "tt5657846", "original_language": "en", "original_title": "Daddy's Home 2", "overview": "Sau thành công của phần 1 vào năm 2015, cha đẻ Dusty (Mark Wahlberg) và cha dượng Brad (Will Ferrell) đã bắt tay nhau để cùng mang tới cho những đứa trẻ của họ một mùa Giáng sinh hoàn hảo. Sự hợp tác mới này đã được thử thách khi mà cha đẻ của Dusty (Mel Gibson) và người cha đa cảm của Brad (John Lithgow) cùng lúc xuất hiện và biến kỳ nghỉ thành một mớ hỗn loạn hoàn toàn.", "popularity": 70.644, "poster_path": "https://image.tmdb.org/t/p/w342/rF2IoKL0IFmumEXQFUuB8LajTYP.jpg", "production_companies": [{"id": 19177, "logo_path": null, "name": "Red Granite Pictures", "origin_country": ""}, {"id": 4740, "logo_path": "/20IuOPEwlHRXnn0MTOsEmw0wcql.png", "name": "Gary Sanchez Productions", "origin_country": "US"}, {"id": 4, "logo_path": "/fycMZt242LVjagMByZOLUGbCvv3.png", "name": "Paramount", "origin_country": "US"}], "production_countries": [{"iso_3166_1": "US", "name": "United States of America"}], "release_date": "2017-11-09", "revenue": 180613180, "runtime": 100, "spoken_languages": [{"english_name": "English", "iso_639_1": "en", "name": "English"}], "status": "Released", "tagline": "More Daddies. More Problems.", "title": "Bố Ngoan, Bố Hư 2", "video": false, "vote_average": 6.3, "vote_count": 1977, "videos": {"results": [{"iso_639_1": "en", "iso_3166_1": "US", "name": "Official Trailer #2", "key": "hTKMUn87SxA", "published_at": "2017-09-06T13:00:04.000Z", "site": "YouTube", "size": 1080, "type": "Trailer", "official": true, "id": "59f70e20925141422102f948"}, {"iso_639_1": "en", "iso_3166_1": "US", "name": "Official Trailer", "key": "huaGQdrkrK0", "published_at": "2017-06-15T16:00:07.000Z", "site": "YouTube", "size": 1080, "type": "Trailer", "official": true, "id": "594330a2c3a3686c59016144"}]}, "credits": {"cast": [{"adult": false, "gender": 2, "id": 23659, "known_for_department": "Acting", "name": "Will Ferrell", "original_name": "Will Ferrell", "popularity": 6.641, "profile_path": "https://image.tmdb.org/t/p/w185/fwzwHyh4bWASls0tGjdNwClfpuS.jpg", "cast_id": 1, "character": "Brad Whitaker", "credit_id": "57f5f6bac3a368160c003927", "order": 0}, {"adult": false, "gender": 2, "id": 13240, "known_for_department": "Acting", "name": "Mark Wahlberg", "original_name": "Mark Wahlberg", "popularity": 19.719, "profile_path": "https://image.tmdb.org/t/p/w185/bTEFpaWd7A6AZVWOqKKBWzKEUe8.jpg", "cast_id": 0, "character": "Dusty Mayron", "credit_id": "57f5f6a8c3a3681610003be3", "order": 1}, {"adult": false, "gender": 2, "id": 12074, "known_for_department": "Acting", "name": "John Lithgow", "original_name": "John Lithgow", "popularity": 5.294, "profile_path": "https://image.tmdb.org/t/p/w185/8Y1sjBdnVR483S8PrnAQzlESwhx.jpg", "cast_id": 10, "character": "Don Whitaker", "credit_id": "5890e8e3c3a368701a008f2b", "order": 2}, {"adult": false, "gender": 2, "id": 2461, "known_for_department": "Acting", "name": "Mel Gibson", "original_name": "Mel Gibson", "popularity": 13.128, "profile_path": "https://image.tmdb.org/t/p/w185/bLzZZRyAsGJvQqsQ1hdptv93aIL.jpg", "cast_id": 9, "character": "Kurt Mayron", "credit_id": "5890e8ddc3a3687010009bf7", "order": 3}, {"adult": false, "gender": 1, "id": 1817, "known_for_department": "Acting", "name": "Linda Cardellini", "original_name": "Linda Cardellini", "popularity": 7.948, "profile_path": "https://image.tmdb.org/t/p/w185/bcycvynDprC1rrhBNrnBjn5uOUd.jpg", "cast_id": 11, "character": "Sara Whitaker", "credit_id": "58d9202c9251411f9006f842", "order": 4}, {"adult": false, "gender": 2, "id": 56446, "known_for_department": "Acting", "name": "John Cena", "original_name": "John Cena", "popularity": 7.932, "profile_path": "https://image.tmdb.org/t/p/w185/rgB2eIOt7WyQjdgJCOuESdDlrjg.jpg", "cast_id": 2, "character": "Roger", "credit_id": "57f5f7029251413613003f71", "order": 5}, {"adult": false, "gender": 1, "id": 207606, "known_for_department": "Acting", "name": "Alessandra Ambrosio", "original_name": "Alessandra Ambrosio", "popularity": 4.777, "profile_path": "https://image.tmdb.org/t/p/w185/nkxU0cLs90wuyRfUMLlo99Neb9N.jpg", "cast_id": 14, "character": "Karen Mayron", "credit_id": "5949eb2dc3a36861b5004b13", "order": 6}, {"adult": false, "gender": 2, "id": 1552636, "known_for_department": "Acting", "name": "Owen Vaccaro", "original_name": "Owen Vaccaro", "popularity": 2.089, "profile_path": "https://image.tmdb.org/t/p/w185/pNTtj9L4eVQQIb6o79D0dJC87HS.jpg", "cast_id": 12, "character": "Dylan Mayron", "credit_id": "58d92078c3a368124f06c6d1", "order": 7}, {"adult": false, "gender": 1, "id": 1512021, "known_for_department": "Acting", "name": "Scarlett Estevez", "original_name": "Scarlett Estevez", "popularity": 13.513, "profile_path": "https://image.tmdb.org/t/p/w185/c8T1SJxcHs0bV1W66qvWVfaINOt.jpg", "cast_id": 13, "character": "Megan Mayron", "credit_id": "58d92092c3a368123406bc24", "order": 8}, {"adult": false, "gender": 1, "id": 1363621, "known_for_department": "Acting", "name": "Didi Costine", "original_name": "Didi Costine", "popularity": 2.286, "profile_path": "https://image.tmdb.org/t/p/w185/nWEWKAgvTOUud8wMYljYrkPnt3g.jpg", "cast_id": 15, "character": "Adrianna", "credit_id": "5949eb6f92514145a8004ab8", "order": 9}, {"adult": false, "gender": 2, "id": 1185286, "known_for_department": "Acting", "name": "Chesley Sullenberger", "original_name": "Chesley Sullenberger", "popularity": 0.6, "profile_path": "https://image.tmdb.org/t/p/w185/r2xvlk0MUAGlnIC1HERStJo7akM.jpg", "cast_id": 17, "character": "Brad's Stepfather", "credit_id": "5a0d029ec3a368130b0053b2", "order": 10}, {"adult": false, "gender": 2, "id": 3896, "known_for_department": "Acting", "name": "Liam Neeson", "original_name": "Liam Neeson", "popularity": 23.845, "profile_path": "https://image.tmdb.org/t/p/w185/bboldwqSC6tdw2iL6631c98l2Mn.jpg", "cast_id": 18, "character": "Himself (voice)", "credit_id": "5a11a859c3a368629204cbd9", "order": 11}, {"adult": false, "gender": 2, "id": 928638, "known_for_department": "Acting", "name": "John Franchi", "original_name": "John Franchi", "popularity": 0.6, "profile_path": null, "cast_id": 19, "character": "Pedestrian", "credit_id": "5ad7722ac3a36847de00f2c3", "order": 12}, {"adult": false, "gender": 1, "id": 1216355, "known_for_department": "Acting", "name": "Andrea Anders", "original_name": "Andrea Anders", "popularity": 2.584, "profile_path": "https://image.tmdb.org/t/p/w185/rTRgTbxzZFdYnnmooOCZ2XHk3vC.jpg", "cast_id": 21, "character": "Principal Hayes", "credit_id": "5dff29b79824c80013e15851", "order": 13}, {"adult": false, "gender": 1, "id": 2487963, "known_for_department": "Acting", "name": "Yamilah Saravong", "original_name": "Yamilah Saravong", "popularity": 0.6, "profile_path": null, "cast_id": 22, "character": "Casey", "credit_id": "5dff29e3d236e600168e2b59", "order": 14}, {"adult": false, "gender": 0, "id": 1664094, "known_for_department": "Acting", "name": "Hector Presedo", "original_name": "Hector Presedo", "popularity": 0.6, "profile_path": null, "cast_id": 23, "character": "Pepe", "credit_id": "5dff29f7d236e600108e45b1", "order": 15}, {"adult": false, "gender": 2, "id": 1566690, "known_for_department": "Acting", "name": "Daniel DiMaggio", "original_name": "Daniel DiMaggio", "popularity": 2.192, "profile_path": "https://image.tmdb.org/t/p/w185/d6CF7v4icnnEpeuueUm2piuR8qH.jpg", "cast_id": 24, "character": "Young Dusty", "credit_id": "5dff2a21d236e600168e2b9c", "order": 16}, {"adult": false, "gender": 0, "id": 1918846, "known_for_department": "Acting", "name": "Yimmy Yim", "original_name": "Yimmy Yim", "popularity": 0.6, "profile_path": null, "cast_id": 25, "character": "Yimmy", "credit_id": "5dff2a6bd236e600108e4a2b", "order": 17}, {"adult": false, "gender": 2, "id": 1593005, "known_for_department": "Acting", "name": "Bill Mootos", "original_name": "Bill Mootos", "popularity": 0.831, "profile_path": null, "cast_id": 26, "character": "Bill", "credit_id": "5dff2a86d1a893001989bc87", "order": 18}, {"adult": false, "gender": 2, "id": 1730745, "known_for_department": "Acting", "name": "Oscar Wahlberg", "original_name": "Oscar Wahlberg", "popularity": 0.996, "profile_path": "https://image.tmdb.org/t/p/w185/6rqiVDXR0wGIHHawd71LrGyjxWe.jpg", "cast_id": 27, "character": "Roberto C. Fishman Pratt", "credit_id": "5dff2aac65686e0018947080", "order": 19}, {"adult": false, "gender": 0, "id": 1456299, "known_for_department": "Acting", "name": "Hillary Olinger", "original_name": "Hillary Olinger", "popularity": 0.6, "profile_path": null, "cast_id": 28, "character": "Ms. Pratt", "credit_id": "5dff2ad165686e001894709f", "order": 20}, {"adult": false, "gender": 0, "id": 2487964, "known_for_department": "Acting", "name": "Sylvia Barjolo", "original_name": "Sylvia Barjolo", "popularity": 0.6, "profile_path": null, "cast_id": 29, "character": "Marlene", "credit_id": "5dff2aecd236e600168e2d10", "order": 21}, {"adult": false, "gender": 0, "id": 1807175, "known_for_department": "Acting", "name": "Matthew Delamater", "original_name": "Matthew Delamater", "popularity": 0.6, "profile_path": null, "cast_id": 30, "character": "Gun Salesman", "credit_id": "5dff2b2a26dac10012614a56", "order": 22}, {"adult": false, "gender": 1, "id": 2506992, "known_for_department": "Acting", "name": "Frankie Francois", "original_name": "Frankie Francois", "popularity": 0.6, "profile_path": "https://image.tmdb.org/t/p/w185/ui9JaZW4ZK71ufr7VjrgiGDvKj.jpg", "cast_id": 111, "character": "Movie Theater Patron (uncredited)", "credit_id": "5e83c29dd236e60013fdc081", "order": 23}, {"adult": false, "gender": 2, "id": 109708, "known_for_department": "Acting", "name": "Bill Burr", "original_name": "Bill Burr", "popularity": 2.727, "profile_path": "https://image.tmdb.org/t/p/w185/q2EjbwF1oDjuwpsTF1BSpKo6RDh.jpg", "cast_id": 112, "character": "Jerry", "credit_id": "5ee6328b97eab4001de36f52", "order": 24}, {"adult": false, "gender": 2, "id": 2188198, "known_for_department": "Acting", "name": "Colton Osorio", "original_name": "Colton Osorio", "popularity": 1.38, "profile_path": "https://image.tmdb.org/t/p/w185/26QYXUN5sa6ZjFCy24y3nnL89SV.jpg", "cast_id": 113, "character": "Little Boy (uncredited)", "credit_id": "60bc0b8deb64f1003fa4b217", "order": 25}, {"adult": false, "gender": 0, "id": 1244097, "known_for_department": "Acting", "name": "Lance Norris", "original_name": "Lance Norris", "popularity": 0.84, "profile_path": null, "cast_id": 114, "character": "Hunter (uncredited)", "credit_id": "61c65dd2a93d250061ad34f4", "order": 26}], "crew": [{"adult": false, "gender": 2, "id": 1589, "known_for_department": "Sound", "name": "Michael Andrews", "original_name": "Michael Andrews", "popularity": 0.6, "profile_path": null, "credit_id": "5dff3065d236e600168e37cd", "department": "Sound", "job": "Music"}, {"adult": false, "gender": 2, "id": 1597, "known_for_department": "Sound", "name": "Michael Payne", "original_name": "Michael Payne", "popularity": 0.6, "profile_path": null, "credit_id": "5dff3558d1a8930014892593", "department": "Sound", "job": "Sound Effects Editor"}, {"adult": false, "gender": 2, "id": 2080, "known_for_department": "Acting", "name": "Todd Bryant", "original_name": "Todd Bryant", "popularity": 0.708, "profile_path": "https://image.tmdb.org/t/p/w185/sauMN1jgnOhafbxMytr2x42kBdG.jpg", "credit_id": "5dff2e6526dac1001761e12f", "department": "Crew", "job": "Stunt Coordinator"}, {"adult": false, "gender": 0, "id": 8157, "known_for_department": "Sound", "name": "Doc Kane", "original_name": "Doc Kane", "popularity": 0.98, "profile_path": null, "credit_id": "5dff34359824c80017e1c095", "department": "Sound", "job": "ADR Mixer"}, {"adult": false, "gender": 1, "id": 10397, "known_for_department": "Costume & Make-Up", "name": "Carol Ramsey", "original_name": "Carol Ramsey", "popularity": 0.98, "profile_path": null, "credit_id": "5dff2c6565686e0013952df3", "department": "Costume & Make-Up", "job": "Costume Design"}, {"adult": false, "gender": 2, "id": 11506, "known_for_department": "Camera", "name": "Julio Macat", "original_name": "Julio Macat", "popularity": 0.611, "profile_path": null, "credit_id": "5dff2b9465686e0013952c01", "department": "Camera", "job": "Director of Photography"}, {"adult": false, "gender": 2, "id": 23659, "known_for_department": "Acting", "name": "Will Ferrell", "original_name": "Will Ferrell", "popularity": 6.641, "profile_path": "https://image.tmdb.org/t/p/w185/fwzwHyh4bWASls0tGjdNwClfpuS.jpg", "credit_id": "588ae26392514156a6011a58", "department": "Production", "job": "Producer"}, {"adult": false, "gender": 2, "id": 37012, "known_for_department": "Editing", "name": "Brad E. Wilhite", "original_name": "Brad E. Wilhite", "popularity": 0.6, "profile_path": null, "credit_id": "5dff2bb0d236e600168e2f7d", "department": "Editing", "job": "Editor"}, {"adult": false, "gender": 2, "id": 29211, "known_for_department": "Crew", "name": "Jay Vinitsky", "original_name": "Jay Vinitsky", "popularity": 0.6, "profile_path": null, "credit_id": "5dff2c8b65686e0013952e53", "department": "Crew", "job": "Post Production Supervisor"}, {"adult": false, "gender": 1, "id": 41080, "known_for_department": "Production", "name": "Allison Jones", "original_name": "Allison Jones", "popularity": 0.98, "profile_path": "https://image.tmdb.org/t/p/w185/d0Kk5DHy2dtoxwX7IelactzN0Hw.jpg", "credit_id": "5dff2be59824c80017e1b801", "department": "Production", "job": "Casting"}, {"adult": false, "gender": 2, "id": 54585, "known_for_department": "Art", "name": "Clayton Hartley", "original_name": "Clayton Hartley", "popularity": 0.6, "profile_path": null, "credit_id": "5dff2c00d1a893001989c175", "department": "Art", "job": "Production Design"}, {"adult": false, "gender": 2, "id": 55710, "known_for_department": "Directing", "name": "Adam McKay", "original_name": "Adam McKay", "popularity": 12.074, "profile_path": "https://image.tmdb.org/t/p/w185/vOyZXNJq7Oo01LPtSD5AZHjctgH.jpg", "credit_id": "588ae27ac3a368413b023f20", "department": "Production", "job": "Producer"}, {"adult": false, "gender": 1, "id": 113045, "known_for_department": "Sound", "name": "Dawn Lunsford", "original_name": "Dawn Lunsford", "popularity": 1.4, "profile_path": "https://image.tmdb.org/t/p/w185/gaGtvXaFT7hZzGc12KsYp91etlh.jpg", "credit_id": "5dff345065686e00159454d0", "department": "Sound", "job": "Foley Artist"}, {"adult": false, "gender": 1, "id": 113090, "known_for_department": "Sound", "name": "Alicia Stevenson", "original_name": "Alicia Stevenson", "popularity": 3.534, "profile_path": "https://image.tmdb.org/t/p/w185/kgYtaWN4VSFh2B0jkHa1GMBOcNU.jpg", "credit_id": "5dff3622d1a893001989d3fc", "department": "Sound", "job": "Foley Artist"}, {"adult": false, "gender": 0, "id": 92343, "known_for_department": "Directing", "name": "Matt Rebenkoff", "original_name": "Matt Rebenkoff", "popularity": 0.98, "profile_path": null, "credit_id": "5dff2e22d1a8930014891a70", "department": "Directing", "job": "First Assistant Director"}, {"adult": false, "gender": 2, "id": 74619, "known_for_department": "Writing", "name": "Sean Anders", "original_name": "Sean Anders", "popularity": 2.744, "profile_path": "https://image.tmdb.org/t/p/w185/vWO1FiGZPOL4FdhbxeykOXRfcXJ.jpg", "credit_id": "588ae23b925141533b0127fc", "department": "Directing", "job": "Director"}, {"adult": false, "gender": 2, "id": 74619, "known_for_department": "Writing", "name": "Sean Anders", "original_name": "Sean Anders", "popularity": 2.744, "profile_path": "https://image.tmdb.org/t/p/w185/vWO1FiGZPOL4FdhbxeykOXRfcXJ.jpg", "credit_id": "588ae2479251411bbe0250c9", "department": "Writing", "job": "Writer"}, {"adult": false, "gender": 0, "id": 74978, "known_for_department": "Sound", "name": "Terry Porter", "original_name": "Terry Porter", "popularity": 1.094, "profile_path": null, "credit_id": "5dff35b1d1a89300148925f0", "department": "Sound", "job": "Sound Re-Recording Mixer"}, {"adult": false, "gender": 2, "id": 90042, "known_for_department": "Crew", "name": "Rene Mousseux", "original_name": "Rene Mousseux", "popularity": 0.6, "profile_path": "https://image.tmdb.org/t/p/w185/rlJeyY5IbWbudi0Ri2f1s9hG3uw.jpg", "credit_id": "5dff2f5f26dac10012615164", "department": "Crew", "job": "Stunt Double"}, {"adult": false, "gender": 0, "id": 28285, "known_for_department": "Sound", "name": "Rick Giovinazzo", "original_name": "Rick Giovinazzo", "popularity": 0.6, "profile_path": null, "credit_id": "5dff38019824c80015e19cf7", "department": "Sound", "job": "Orchestrator"}, {"adult": false, "gender": 2, "id": 202648, "known_for_department": "Writing", "name": "Brian Burns", "original_name": "Brian Burns", "popularity": 0.6, "profile_path": null, "credit_id": "5dff2b74d1a893001288da46", "department": "Writing", "job": "Characters"}, {"adult": false, "gender": 1, "id": 204408, "known_for_department": "Acting", "name": "Helena Barrett", "original_name": "Helena Barrett", "popularity": 2.26, "profile_path": "https://image.tmdb.org/t/p/w185/3etCIazLPUAUDWW4qKEsFPnPcsp.jpg", "credit_id": "5dff2e8626dac1001761e143", "department": "Crew", "job": "Stunt Double"}, {"adult": false, "gender": 2, "id": 212576, "known_for_department": "Writing", "name": "John Morris", "original_name": "John Morris", "popularity": 1.614, "profile_path": "https://image.tmdb.org/t/p/w185/dI4L5EBAPLlxocjIcGUtB7YHZqY.jpg", "credit_id": "588ae253925141533b01280f", "department": "Writing", "job": "Writer"}, {"adult": false, "gender": 2, "id": 1031764, "known_for_department": "Sound", "name": "Darren Sunny Warkentin", "original_name": "Darren Sunny Warkentin", "popularity": 0.6, "profile_path": null, "credit_id": "5dff368bd1a89300148927a1", "department": "Sound", "job": "Supervising Sound Editor"}, {"adult": false, "gender": 0, "id": 1031811, "known_for_department": "Sound", "name": "Andrew DeCristofaro", "original_name": "Andrew DeCristofaro", "popularity": 0.6, "profile_path": null, "credit_id": "5dff33639824c80017e1bfc1", "department": "Sound", "job": "Supervising Sound Editor"}, {"adult": false, "gender": 0, "id": 1095093, "known_for_department": "Costume & Make-Up", "name": "Bridget Cook", "original_name": "Bridget Cook", "popularity": 0.6, "profile_path": null, "credit_id": "5dff2d0226dac100146234c3", "department": "Costume & Make-Up", "job": "Hair Department Head"}, {"adult": false, "gender": 2, "id": 1242111, "known_for_department": "Art", "name": "Jeremy Woodward", "original_name": "Jeremy Woodward", "popularity": 1.96, "profile_path": null, "credit_id": "5dff32bb65686e001594530a", "department": "Art", "job": "Set Designer"}, {"adult": false, "gender": 0, "id": 1283905, "known_for_department": "Crew", "name": "Patrick Ruth", "original_name": "Patrick Ruth", "popularity": 0.6, "profile_path": null, "credit_id": "5dff3a8365686e001894909f", "department": "Camera", "job": "Camera Operator"}, {"adult": false, "gender": 0, "id": 1301652, "known_for_department": "Crew", "name": "Stephen W. Schriver", "original_name": "Stephen W. Schriver", "popularity": 0.6, "profile_path": null, "credit_id": "5dff2f2365686e00189478ec", "department": "Crew", "job": "Stunt Double"}, {"adult": false, "gender": 0, "id": 1318465, "known_for_department": "Costume & Make-Up", "name": "Aimee McCue", "original_name": "Aimee McCue", "popularity": 0.6, "profile_path": null, "credit_id": "5dff389a26dac100146246d5", "department": "Costume & Make-Up", "job": "Key Costumer"}, {"adult": false, "gender": 1, "id": 1321011, "known_for_department": "Art", "name": "Debbie Cutler", "original_name": "Debbie Cutler", "popularity": 0.6, "profile_path": null, "credit_id": "5dff2c389824c80013e15cb2", "department": "Art", "job": "Set Decoration"}, {"adult": false, "gender": 0, "id": 1334462, "known_for_department": "Art", "name": "Joseph Kearney", "original_name": "Joseph Kearney", "popularity": 0.6, "profile_path": null, "credit_id": "588ae28b9251411bbe0250f7", "department": "Art", "job": "Construction Coordinator"}, {"adult": false, "gender": 1, "id": 1352977, "known_for_department": "Costume & Make-Up", "name": "Valerie Zielonka", "original_name": "Valerie Zielonka", "popularity": 0.98, "profile_path": null, "credit_id": "5dff392126dac10012616374", "department": "Costume & Make-Up", "job": "Costume Supervisor"}, {"adult": false, "gender": 1, "id": 1377293, "known_for_department": "Sound", "name": "Karen Vassar Triest", "original_name": "Karen Vassar Triest", "popularity": 0.6, "profile_path": null, "credit_id": "5dff3664d236e600168e453e", "department": "Sound", "job": "Sound Effects Editor"}, {"adult": false, "gender": 2, "id": 1387183, "known_for_department": "Sound", "name": "John C. Stuver", "original_name": "John C. Stuver", "popularity": 0.98, "profile_path": null, "credit_id": "5dff3641d1a893001989d4a3", "department": "Sound", "job": "Dialogue Editor"}, {"adult": false, "gender": 2, "id": 1395023, "known_for_department": "Sound", "name": "Bill R. Dean", "original_name": "Bill R. Dean", "popularity": 0.702, "profile_path": null, "credit_id": "5dff3348d1a8930014891efd", "department": "Sound", "job": "Sound Effects Editor"}, {"adult": false, "gender": 1, "id": 1400534, "known_for_department": "Camera", "name": "Claire Folger", "original_name": "Claire Folger", "popularity": 1.166, "profile_path": null, "credit_id": "5dff39ad9824c80013e1752c", "department": "Camera", "job": "Still Photographer"}, {"adult": false, "gender": 1, "id": 1401687, "known_for_department": "Sound", "name": "Anna Behlmer", "original_name": "Anna Behlmer", "popularity": 0.6, "profile_path": "https://image.tmdb.org/t/p/w185/kUsjqvtj653USV4FXxJmPiqJCW4.jpg", "credit_id": "5dff3309d1a8930014891ed6", "department": "Sound", "job": "Sound Re-Recording Mixer"}, {"adult": false, "gender": 1, "id": 1405232, "known_for_department": "Sound", "name": "Laura Harris Atkinson", "original_name": "Laura Harris Atkinson", "popularity": 0.6, "profile_path": null, "credit_id": "5dff32e3d1a893001288e95c", "department": "Sound", "job": "Dialogue Editor"}, {"adult": false, "gender": 2, "id": 1406826, "known_for_department": "Sound", "name": "Hector C. Gika", "original_name": "Hector C. Gika", "popularity": 0.84, "profile_path": "https://image.tmdb.org/t/p/w185/1yJ3xp1jj4Az44n6fdIw4F6lCz6.jpg", "credit_id": "5dff33e4d236e600108e56fc", "department": "Sound", "job": "Sound Effects Editor"}, {"adult": false, "gender": 0, "id": 1408395, "known_for_department": "Lighting", "name": "Frans Wetterings III", "original_name": "Frans Wetterings III", "popularity": 0.6, "profile_path": null, "credit_id": "5dff3abdd1a893001288f5eb", "department": "Lighting", "job": "Chief Lighting Technician"}, {"adult": false, "gender": 2, "id": 1412643, "known_for_department": "Sound", "name": "Ryan Young", "original_name": "Ryan Young", "popularity": 0.6, "profile_path": null, "credit_id": "5dff36f626dac1001761f0d9", "department": "Sound", "job": "ADR Recordist"}, {"adult": false, "gender": 0, "id": 1440272, "known_for_department": "Editing", "name": "Brett Carroll", "original_name": "Brett Carroll", "popularity": 0.6, "profile_path": null, "credit_id": "5dff375f26dac1001761f163", "department": "Editing", "job": "First Assistant Editor"}, {"adult": false, "gender": 1, "id": 1447941, "known_for_department": "Costume & Make-Up", "name": "Nichole Pleau", "original_name": "Nichole Pleau", "popularity": 0.6, "profile_path": null, "credit_id": "5dff2d6b26dac10014623541", "department": "Costume & Make-Up", "job": "Key Makeup Artist"}, {"adult": false, "gender": 2, "id": 1449446, "known_for_department": "Editing", "name": "Matt Willard", "original_name": "Matt Willard", "popularity": 0.994, "profile_path": null, "credit_id": "5dff37c2d1a893001288ee7a", "department": "Editing", "job": "Assistant Editor"}, {"adult": false, "gender": 2, "id": 1459221, "known_for_department": "Sound", "name": "Brian Magrum", "original_name": "Brian Magrum", "popularity": 0.6, "profile_path": null, "credit_id": "5dff347ed236e600168e424d", "department": "Sound", "job": "ADR Mixer"}, {"adult": false, "gender": 0, "id": 1461169, "known_for_department": "Sound", "name": "Gayle Wesley", "original_name": "Gayle Wesley", "popularity": 0.6, "profile_path": null, "credit_id": "5dff36c29824c80017e1c7dd", "department": "Sound", "job": "Foley Editor"}, {"adult": false, "gender": 1, "id": 1464955, "known_for_department": "Costume & Make-Up", "name": "Cheryl Daniels", "original_name": "Cheryl Daniels", "popularity": 0.98, "profile_path": null, "credit_id": "5dff2d1c65686e0018947506", "department": "Costume & Make-Up", "job": "Key Hair Stylist"}, {"adult": false, "gender": 1, "id": 1478953, "known_for_department": "Directing", "name": "Cate Hardman", "original_name": "Cate Hardman", "popularity": 1.4, "profile_path": null, "credit_id": "5dff2fa426dac100126151bb", "department": "Directing", "job": "Script Supervisor"}, {"adult": false, "gender": 2, "id": 1491848, "known_for_department": "Sound", "name": "Chris Navarro", "original_name": "Chris Navarro", "popularity": 0.98, "profile_path": null, "credit_id": "5dff34fed236e600168e4303", "department": "Sound", "job": "ADR Mixer"}, {"adult": false, "gender": 0, "id": 1494535, "known_for_department": "Costume & Make-Up", "name": "Liz Pecos", "original_name": "Liz Pecos", "popularity": 0.6, "profile_path": null, "credit_id": "5dff38bb9824c80017e1ce68", "department": "Costume & Make-Up", "job": "Costume Supervisor"}, {"adult": false, "gender": 0, "id": 1500286, "known_for_department": "Sound", "name": "Carl Sealove", "original_name": "Carl Sealove", "popularity": 0.6, "profile_path": null, "credit_id": "5dff3826d236e600108e6050", "department": "Sound", "job": "Music Editor"}, {"adult": false, "gender": 0, "id": 1506368, "known_for_department": "Costume & Make-Up", "name": "Autumn Butler", "original_name": "Autumn Butler", "popularity": 0.6, "profile_path": null, "credit_id": "5dff2ce1d1a893001288dd0b", "department": "Costume & Make-Up", "job": "Makeup Department Head"}, {"adult": false, "gender": 0, "id": 1532245, "known_for_department": "Costume & Make-Up", "name": "Senna Shanti", "original_name": "Senna Shanti", "popularity": 1.38, "profile_path": null, "credit_id": "5dff38e826dac100126162f7", "department": "Costume & Make-Up", "job": "Assistant Costume Designer"}, {"adult": false, "gender": 0, "id": 1537105, "known_for_department": "Costume & Make-Up", "name": "Juliet Loveland", "original_name": "Juliet Loveland", "popularity": 0.6, "profile_path": null, "credit_id": "5dff2d44d1a893001989c330", "department": "Costume & Make-Up", "job": "Makeup Artist"}, {"adult": false, "gender": 0, "id": 1543203, "known_for_department": "Art", "name": "Rachel Block", "original_name": "Rachel Block", "popularity": 0.98, "profile_path": null, "credit_id": "5dff2c1fd236e600108e4dc3", "department": "Art", "job": "Art Direction"}, {"adult": false, "gender": 0, "id": 1550832, "known_for_department": "Sound", "name": "Ed Novick", "original_name": "Ed Novick", "popularity": 0.6, "profile_path": null, "credit_id": "5c1077b60e0a2638b80f097e", "department": "Sound", "job": "Sound Mixer"}, {"adult": false, "gender": 0, "id": 1575619, "known_for_department": "Camera", "name": "Christian Gibson", "original_name": "Christian Gibson", "popularity": 0.6, "profile_path": null, "credit_id": "5dff39f3d1a893001288f3fe", "department": "Camera", "job": "Steadicam Operator"}, {"adult": false, "gender": 0, "id": 1608760, "known_for_department": "Art", "name": "Chris Sullivan", "original_name": "Chris Sullivan", "popularity": 0.6, "profile_path": null, "credit_id": "5dff327165686e00159451db", "department": "Art", "job": "Art Department Coordinator"}, {"adult": false, "gender": 2, "id": 1717724, "known_for_department": "Production", "name": "Ben Harris", "original_name": "Ben Harris", "popularity": 0.6, "profile_path": "https://image.tmdb.org/t/p/w185/p56oMFwshowbC049JPoO5h2qMwm.jpg", "credit_id": "5dff2bd326dac1001462337c", "department": "Production", "job": "Casting"}, {"adult": false, "gender": 0, "id": 1729094, "known_for_department": "Art", "name": "Anthony Raymond", "original_name": "Anthony Raymond", "popularity": 0.6, "profile_path": null, "credit_id": "5dff313f9824c80017e1be5d", "department": "Art", "job": "Set Designer"}, {"adult": false, "gender": 2, "id": 1737654, "known_for_department": "Sound", "name": "Judah Getz", "original_name": "Judah Getz", "popularity": 0.6, "profile_path": null, "credit_id": "5dff33b9d236e600168e4177", "department": "Sound", "job": "ADR Mixer"}, {"adult": false, "gender": 2, "id": 1737660, "known_for_department": "Sound", "name": "David Jobe", "original_name": "David Jobe", "popularity": 0.6, "profile_path": "https://image.tmdb.org/t/p/w185/wej0TWRlW8mKuIQd5F8JMu7owdG.jpg", "credit_id": "5dff341326dac1001761e7dc", "department": "Sound", "job": "Foley Mixer"}, {"adult": false, "gender": 0, "id": 1739772, "known_for_department": "Art", "name": "Ashley L. Sykes", "original_name": "Ashley L. Sykes", "popularity": 0.6, "profile_path": null, "credit_id": "5dff3294d1a893001989cdf9", "department": "Art", "job": "Set Decorating Coordinator"}, {"adult": false, "gender": 1, "id": 1739777, "known_for_department": "Costume & Make-Up", "name": "Elizabeth Clifford", "original_name": "Elizabeth Clifford", "popularity": 0.6, "profile_path": null, "credit_id": "5dff3871d236e600168e4982", "department": "Costume & Make-Up", "job": "Key Costumer"}, {"adult": false, "gender": 0, "id": 1739780, "known_for_department": "Camera", "name": "John Garrett", "original_name": "John Garrett", "popularity": 0.6, "profile_path": null, "credit_id": "5dff39df26dac1001761f442", "department": "Camera", "job": "Camera Operator"}, {"adult": false, "gender": 0, "id": 1760561, "known_for_department": "Crew", "name": "Steven Blizzard", "original_name": "Steven Blizzard", "popularity": 0.6, "profile_path": null, "credit_id": "5dff395ad236e600128e5578", "department": "Camera", "job": "Drone Pilot"}, {"adult": false, "gender": 0, "id": 1769079, "known_for_department": "Sound", "name": "Joel Reidy", "original_name": "Joel Reidy", "popularity": 0.6, "profile_path": null, "credit_id": "5dff35eed236e600128e5281", "department": "Sound", "job": "Boom Operator"}, {"adult": false, "gender": 0, "id": 1769789, "known_for_department": "Art", "name": "Morgan Kling", "original_name": "Morgan Kling", "popularity": 0.6, "profile_path": null, "credit_id": "5dff30ee65686e00139535c2", "department": "Art", "job": "Property Master"}, {"adult": false, "gender": 2, "id": 1841285, "known_for_department": "Art", "name": "Steve Brennan", "original_name": "Steve Brennan", "popularity": 0.6, "profile_path": null, "credit_id": "5dff31abd1a893001989cb7d", "department": "Art", "job": "Assistant Property Master"}, {"adult": false, "gender": 0, "id": 1904006, "known_for_department": "Production", "name": "Shari LaFranchi Blakney", "original_name": "Shari LaFranchi Blakney", "popularity": 0.6, "profile_path": null, "credit_id": "5dff300265686e0015944ca9", "department": "Production", "job": "Production Coordinator"}, {"adult": false, "gender": 2, "id": 1994224, "known_for_department": "Sound", "name": "Thomas J. O'Connell", "original_name": "Thomas J. O'Connell", "popularity": 1.4, "profile_path": null, "credit_id": "5dff35329824c80017e1c3d1", "department": "Sound", "job": "ADR Mixer"}, {"adult": false, "gender": 0, "id": 2105488, "known_for_department": "Costume & Make-Up", "name": "Jennifer Lynn Tremblay", "original_name": "Jennifer Lynn Tremblay", "popularity": 0.6, "profile_path": null, "credit_id": "5dff390465686e0015945bea", "department": "Costume & Make-Up", "job": "Tailor"}, {"adult": false, "gender": 0, "id": 2137984, "known_for_department": "Crew", "name": "Joann Connolly", "original_name": "Joann Connolly", "popularity": 0.6, "profile_path": null, "credit_id": "5dff2de19824c80013e16126", "department": "Directing", "job": "Second Assistant Director"}, {"adult": false, "gender": 0, "id": 2149470, "known_for_department": "Crew", "name": "Mark Menard", "original_name": "Mark Menard", "popularity": 0.6, "profile_path": null, "credit_id": "5dff320526dac100126158c3", "department": "Art", "job": "Construction Foreman"}, {"adult": false, "gender": 0, "id": 2149479, "known_for_department": "Art", "name": "Adam McClain", "original_name": "Adam McClain", "popularity": 0.6, "profile_path": null, "credit_id": "5dff31f765686e0013953868", "department": "Art", "job": "Construction Foreman"}, {"adult": false, "gender": 0, "id": 2149494, "known_for_department": "Crew", "name": "Paula Bird", "original_name": "Paula Bird", "popularity": 0.6, "profile_path": null, "credit_id": "5dff316526dac10014623b20", "department": "Art", "job": "Painter"}, {"adult": false, "gender": 1, "id": 2161465, "known_for_department": "Crew", "name": "Juliana Potter", "original_name": "Juliana Potter", "popularity": 0.6, "profile_path": null, "credit_id": "5dff2ee665686e0013953324", "department": "Crew", "job": "Stunt Double"}, {"adult": false, "gender": 2, "id": 2193910, "known_for_department": "Camera", "name": "Chris Malenfant", "original_name": "Chris Malenfant", "popularity": 0.6, "profile_path": null, "credit_id": "5dff3a3a65686e0015945e82", "department": "Camera", "job": "Epk Camera Operator"}, {"adult": false, "gender": 2, "id": 2246643, "known_for_department": "Editing", "name": "Roger Cooper", "original_name": "Roger Cooper", "popularity": 0.6, "profile_path": null, "credit_id": "5dff3787d236e600128e53c9", "department": "Editing", "job": "First Assistant Editor"}, {"adult": false, "gender": 0, "id": 2487967, "known_for_department": "Costume & Make-Up", "name": "Joanna Raskin", "original_name": "Joanna Raskin", "popularity": 0.6, "profile_path": null, "credit_id": "5dff2db126dac1001761e017", "department": "Costume & Make-Up", "job": "Hairstylist"}, {"adult": false, "gender": 0, "id": 2487969, "known_for_department": "Crew", "name": "Mark Freeman Schotz", "original_name": "Mark Freeman Schotz", "popularity": 0.6, "profile_path": null, "credit_id": "5dff2efe26dac1001462379e", "department": "Crew", "job": "Stunt Double"}, {"adult": false, "gender": 0, "id": 2487972, "known_for_department": "Art", "name": "Lima Hyelim Kang", "original_name": "Lima Hyelim Kang", "popularity": 0.6, "profile_path": null, "credit_id": "5dff31db65686e00139537c2", "department": "Art", "job": "Graphic Designer"}, {"adult": false, "gender": 0, "id": 2487974, "known_for_department": "Art", "name": "David T. Parsons", "original_name": "David T. Parsons", "popularity": 0.6, "profile_path": null, "credit_id": "5dff321665686e00139538a4", "department": "Art", "job": "Construction Foreman"}, {"adult": false, "gender": 0, "id": 2487975, "known_for_department": "Art", "name": "James Rocci", "original_name": "James Rocci", "popularity": 0.6, "profile_path": null, "credit_id": "5dff32369824c80013e16925", "department": "Art", "job": "Set Designer"}, {"adult": false, "gender": 1, "id": 2487977, "known_for_department": "Sound", "name": "Jeannette Browning", "original_name": "Jeannette Browning", "popularity": 0.6, "profile_path": null, "credit_id": "5dff331c26dac10012615a18", "department": "Sound", "job": "ADR Recordist"}, {"adult": false, "gender": 0, "id": 2487984, "known_for_department": "Costume & Make-Up", "name": "Margaret Galvin", "original_name": "Margaret Galvin", "popularity": 0.98, "profile_path": null, "credit_id": "5dff3886d1a893001288f12a", "department": "Costume & Make-Up", "job": "Costume Coordinator"}]}, "reviews": {"page": 1, "results": [{"author": "r96sk", "author_details": {"name": "", "username": "r96sk", "avatar_path": "/https://secure.gravatar.com/avatar/96c2e0e4ac98450f9e8e3c0a0a40aad8.jpg", "rating": 7.0}, "content": "Like the first film, <em>'Daddy’s Home 2'</em> is nothing special but isn't bad either. A fine watch, nothing more or less.\r\n\r\nThe plot doesn't have nearly as many laughs as it needs, with that said there are a couple of decent bits - and some weird parts, particularly one at the end. Talking of the end, it's very cringe. Mark Wahlberg (Dusty) is probably the best onscreen, Will Ferrell (Brad) does well enough too.\r\n\r\nMel Gibson (Kurt) and John Lithgow (Don) are two newcomers. Both have one or two moments, though nothing more - I liked Lithgow the most. I kinda, somewhat randomly, felt Kurt Russell would've made a much better Kurt - didn't even clock the name clash before having that thought either, funnily enough. Linda Cardellini, meanwhile, is alright.\r\n\r\nIt needed more, but it's nothing notably worse than its predecessor which is always a positive for a sequel.", "created_at": "2021-02-23T00:00:36.557Z", "id": "603445a4be55b7003e953005", "updated_at": "2021-06-23T15:58:52.177Z", "url": "https://www.themoviedb.org/review/603445a4be55b7003e953005"}], "total_pages": 1, "total_results": 1}}